MANIFEST.in
requirements.txt
setup.py
test_requirements.txt
version.txt
cloudshell/__init__.py
cloudshell/networking/__init__.py
cloudshell/networking/brocade/__init__.py
cloudshell/networking/brocade/netiron/__init__.py
cloudshell/networking/brocade/netiron/netiron_configuration.py
cloudshell/networking/brocade/netiron/netiron_resource_driver.py
cloudshell/networking/brocade/netiron/autoload/__init__.py
cloudshell/networking/brocade/netiron/autoload/brocade_netiron_snmp_autoload.py
cloudshell/networking/brocade/netiron/handler/__init__.py
cloudshell/networking/brocade/netiron/handler/brocade_netiron_configuration_operations.py
cloudshell/networking/brocade/netiron/handler/brocade_netiron_connectivity_operations.py
cloudshell_networking_brocade_netiron.egg-info/PKG-INFO
cloudshell_networking_brocade_netiron.egg-info/SOURCES.txt
cloudshell_networking_brocade_netiron.egg-info/dependency_links.txt
cloudshell_networking_brocade_netiron.egg-info/requires.txt
cloudshell_networking_brocade_netiron.egg-info/top_level.txt