Metadata-Version: 1.0
Name: cloudshell-networking-brocade-netiron
Version: 1.0.32
Summary: QualiSystems Brocade NetIron package
Home-page: http://www.qualisystems.com/
Author: QualiSystems
Author-email: info@qualisystems.com
License: UNKNOWN
Platform: UNKNOWN
